pinyin_segmenter/__init__.py
pinyin_segmenter/core.py
pinyin_segmenter-0.1.0.dist-info/METADATA
pinyin_segmenter-0.1.0.dist-info/WHEEL
pinyin_segmenter-0.1.0.dist-info/top_level.txt
pinyin_segmenter-0.1.0.dist-info/RECORD
