Metadata-Version: 2.4
Name: pinyin-segmenter
Version: 0.1.0
Summary: 拼音分割器，用于将连续的拼音字符串分割为有效的拼音片段
Author: rRR0VrFP
Maintainer: rRR0VrFP
License: MIT
Keywords: pinyin,segmenter,chinese,nlp
Classifier: Development Status :: 5 - Production/Stable
Classifier: Intended Audience :: Developers
Classifier: License :: OSI Approved :: MIT License
Classifier: Operating System :: OS Independent
Classifier: Programming Language :: Python :: 3
Classifier: Programming Language :: Python :: 3.8
Classifier: Programming Language :: Python :: 3.9
Classifier: Programming Language :: Python :: 3.10
Classifier: Programming Language :: Python :: 3.11
Classifier: Programming Language :: Python :: 3.12
Classifier: Topic :: Text Processing :: Linguistic
Classifier: Topic :: Software Development :: Libraries :: Python Modules
Requires-Python: >=3.9
Requires-Dist: pypinyin
